ECM1400_CA_CODE/__init__.py
ECM1400_CA_CODE/config.py
ECM1400_CA_CODE/covid_data_handler.py
ECM1400_CA_CODE/covid_data_interface.py
ECM1400_CA_CODE/handlers_logging.py
ECM1400_CA_CODE/news_data_handling.py
ECM1400_CA_CODE/test_config.py
ECM1400_CA_CODE/test_covid_data_handler.py
ECM1400_CA_CODE/test_covid_data_interface.py
ECM1400_CA_CODE/test_news_data_handling.py
Covid_19_Dashboard_Samuel_Thomas_CA_Yr1-0.0.1.dist-info/LICENSE
Covid_19_Dashboard_Samuel_Thomas_CA_Yr1-0.0.1.dist-info/METADATA
Covid_19_Dashboard_Samuel_Thomas_CA_Yr1-0.0.1.dist-info/WHEEL
Covid_19_Dashboard_Samuel_Thomas_CA_Yr1-0.0.1.dist-info/top_level.txt
Covid_19_Dashboard_Samuel_Thomas_CA_Yr1-0.0.1.dist-info/RECORD
