Metadata-Version: 2.1
Name: Covid-19-Dashboard-Samuel-Thomas-CA-Yr1
Version: 0.0.1
Summary: A module to create and communicate with a covid 19 flask dashboard
Home-page: https://pypi.org/project/Covid 19 Dashboard - Samuel Thomas CA Yr1/
Author: Samuel Thomas
Author-email: scct201@exeter.ac.uk
License: UNKNOWN
Platform: UNKNOWN
Classifier: Programming Language :: Python :: 3
Classifier: License :: OSI Approved :: MIT License
Requires-Python: >-3.6
License-File: LICENSE
